django_template_tags/__init__.py
django_template_tags/template_callable.py
django_template_tags/static/css/stylize.css
django_template_tags/templatetags/__init__.py
django_template_tags/templatetags/call.py
django_template_tags/templatetags/debug.py
django_template_tags/templatetags/decorate.py
django_template_tags/templatetags/macro.py
django_template_tags/templatetags/stylize.py
django_template_tags-1.1.3.dist-info/DESCRIPTION.rst
django_template_tags-1.1.3.dist-info/METADATA
django_template_tags-1.1.3.dist-info/RECORD
django_template_tags-1.1.3.dist-info/WHEEL
django_template_tags-1.1.3.dist-info/metadata.json
django_template_tags-1.1.3.dist-info/top_level.txt
