Metadata-Version: 2.0
Name: django-template-tags
Version: 1.1.3
Summary: Some general, useful template tags.
Home-page: https://github.com/vikingco/django-template-tags
Author: Jonathan Slenders, Unleashed NV
Author-email: operations@unleashed.be
License: BSD
Platform: UNKNOWN
Classifier: Intended Audience :: Developers
Classifier: Programming Language :: Python
Classifier: Operating System :: OS Independent
Classifier: Environment :: Web Environment
Classifier: Framework :: Django
